cenclave_lib_crypto/__init__.py
cenclave_lib_crypto/conversion.py
cenclave_lib_crypto/ed25519.py
cenclave_lib_crypto/error.py
cenclave_lib_crypto/py.typed
cenclave_lib_crypto/seal_box.py
cenclave_lib_crypto/x25519.py
cenclave_lib_crypto/xsalsa20_poly1305.py
cenclave_lib_crypto-1.0.0.dist-info/METADATA
cenclave_lib_crypto-1.0.0.dist-info/WHEEL
cenclave_lib_crypto-1.0.0.dist-info/top_level.txt
cenclave_lib_crypto-1.0.0.dist-info/RECORD
